viewgeom/__init__.py
viewgeom-0.1.4.dist-info/METADATA
viewgeom-0.1.4.dist-info/WHEEL
viewgeom-0.1.4.dist-info/entry_points.txt
viewgeom-0.1.4.dist-info/licenses/LICENSE
viewgeom-0.1.4.dist-info/RECORD
