Metadata-Version: 2.4
Name: viewgeom
Version: 0.1.4
Summary: Command line vector viewer for .shp, .geojson, .gpkg, .geoparquet, .kml, and .kmz with a simple Qt UI.
Project-URL: Homepage, https://github.com/nkeikon/geomviewer
Project-URL: Repository, https://github.com/nkeikon/geomviewer
Project-URL: Issues, https://github.com/nkeikon/geomviewer/issues
Author: Keiko Nomura
License: MIT
License-File: LICENSE
Classifier: Intended Audience :: Science/Research
Classifier: License :: OSI Approved :: MIT License
Classifier: Operating System :: OS Independent
Classifier: Programming Language :: Python :: 3
Classifier: Topic :: Scientific/Engineering :: GIS
Requires-Python: >=3.9
Requires-Dist: geopandas>=0.13
Requires-Dist: matplotlib>=3.7
Requires-Dist: numpy>=1.23
Requires-Dist: pandas>=2.0
Requires-Dist: pyogrio>=0.7
Requires-Dist: pyside6>=6.5
Requires-Dist: requests
Requires-Dist: shapely>=2.0
Provides-Extra: duckdb
Requires-Dist: duckdb>=1.0.0; extra == 'duckdb'
Provides-Extra: parquet
Requires-Dist: pyarrow>=12; extra == 'parquet'
